highsbox-1.11.0.data/purelib/highsbox/__init__.py
highsbox-1.11.0.data/purelib/highsbox/__main__.py
highsbox-1.11.0.data/purelib/highsbox/highs_dist/bin/highs
highsbox-1.11.0.data/purelib/highsbox/highs_dist/include/highs_export.h
highsbox-1.11.0.data/purelib/highsbox/highs_dist/include/highs/HConfig.h
highsbox-1.11.0.data/purelib/highsbox/highs_dist/include/highs/Highs.h
highsbox-1.11.0.data/purelib/highsbox/highs_dist/include/highs/filereaderlp/builder.hpp
highsbox-1.11.0.data/purelib/highsbox/highs_dist/include/highs/filereaderlp/def.hpp
highsbox-1.11.0.data/purelib/highsbox/highs_dist/include/highs/filereaderlp/model.hpp
highsbox-1.11.0.data/purelib/highsbox/highs_dist/include/highs/filereaderlp/reader.hpp
highsbox-1.11.0.data/purelib/highsbox/highs_dist/include/highs/interfaces/highs_c_api.h
highsbox-1.11.0.data/purelib/highsbox/highs_dist/include/highs/io/Filereader.h
highsbox-1.11.0.data/purelib/highsbox/highs_dist/include/highs/io/FilereaderEms.h
highsbox-1.11.0.data/purelib/highsbox/highs_dist/include/highs/io/FilereaderLp.h
highsbox-1.11.0.data/purelib/highsbox/highs_dist/include/highs/io/FilereaderMps.h
highsbox-1.11.0.data/purelib/highsbox/highs_dist/include/highs/io/HMPSIO.h
highsbox-1.11.0.data/purelib/highsbox/highs_dist/include/highs/io/HMpsFF.h
highsbox-1.11.0.data/purelib/highsbox/highs_dist/include/highs/io/HighsIO.h
highsbox-1.11.0.data/purelib/highsbox/highs_dist/include/highs/io/LoadOptions.h
highsbox-1.11.0.data/purelib/highsbox/highs_dist/include/highs/ipm/IpxSolution.h
highsbox-1.11.0.data/purelib/highsbox/highs_dist/include/highs/ipm/IpxWrapper.h
highsbox-1.11.0.data/purelib/highsbox/highs_dist/include/highs/ipm/basiclu/basiclu.h
highsbox-1.11.0.data/purelib/highsbox/highs_dist/include/highs/ipm/basiclu/basiclu_factorize.h
highsbox-1.11.0.data/purelib/highsbox/highs_dist/include/highs/ipm/basiclu/basiclu_get_factors.h
highsbox-1.11.0.data/purelib/highsbox/highs_dist/include/highs/ipm/basiclu/basiclu_initialize.h
highsbox-1.11.0.dist-info/METADATA
highsbox-1.11.0.dist-info/WHEEL
highsbox-1.11.0.dist-info/top_level.txt
highsbox-1.11.0.dist-info/RECORD
