Metadata-Version: 2.4
Name: highsbox
Version: 1.11.0
Summary: highsbox: binary distribution of HiGHS optimizer
Home-page: https://github.com/metab0t/highsbox
Author: Yue Yang
Author-email: metab0t@outlook.com
License: MIT
Dynamic: author
Dynamic: author-email
Dynamic: description
Dynamic: description-content-type
Dynamic: home-page
Dynamic: license
Dynamic: summary
